[{"id":"jtp-1","setIdJa":"jtp","nameJa":"ウパー","nameEn":"Wooper","types":["Water"],"imageJa":"images/sets/jtp/jp/121.jpg","imageEn":null,"enAvailable":false},{"id":"jtp-2","setIdJa":"jtp","nameJa":"ヌオー","nameEn":"Quagsire","types":["Water"],"imageJa":"images/sets/jtp/jp/122.jpg","imageEn":null,"enAvailable":false},{"id":"jtp-3","setIdJa":"jtp","nameJa":"フラミゴex","nameEn":"Flamigo ex","types":["Colorless"],"imageJa":"images/sets/jtp/jp/124.jpg","imageEn":null,"enAvailable":false},{"id":"jtp-4","setIdJa":"jtp","nameJa":"ネストボール","nameEn":"Nest Ball","types":[],"imageJa":"images/sets/jtp/jp/125.jpg","imageEn":null,"enAvailable":false},{"id":"jtp-5","setIdJa":"jtp","nameJa":"ポケモンいれかえ","nameEn":"Switch","types":[],"imageJa":"images/sets/jtp/jp/126.jpg","imageEn":null,"enAvailable":false},{"id":"jtp-6","setIdJa":"jtp","nameJa":"ライム","nameEn":"Ryme","types":[],"imageJa":"images/sets/jtp/jp/127.jpg","imageEn":null,"enAvailable":false},{"id":"jtp-7","setIdJa":"jtp","nameJa":"チリ","nameEn":"Rika","types":[],"imageJa":"images/sets/jtp/jp/128.jpg","imageEn":null,"enAvailable":false},{"id":"jtp-8","setIdJa":"jtp","nameJa":"マツバの確信","nameEn":"Morty's Conviction","types":[],"imageJa":"images/sets/jtp/jp/147.jpg","imageEn":null,"enAvailable":false},{"id":"jtp-9","setIdJa":"jtp","nameJa":"なかよしポフィン","nameEn":"Buddy-Buddy Poffin","types":[],"imageJa":"images/sets/jtp/jp/150.jpg","imageEn":null,"enAvailable":false},{"id":"jtp-10","setIdJa":"jtp","nameJa":"ミライドン","nameEn":"Miraidon","types":["Lightning"],"imageJa":"images/sets/jtp/jp/151.jpg","imageEn":null,"enAvailable":false},{"id":"jtp-11","setIdJa":"jtp","nameJa":"コライドン","nameEn":"Koraidon","types":["Dragon"],"imageJa":"images/sets/jtp/jp/152.jpg","imageEn":null,"enAvailable":false},{"id":"jtp-12","setIdJa":"jtp","nameJa":"ネモ","nameEn":"Nemona","types":[],"imageJa":"images/sets/jtp/jp/153.jpg","imageEn":null,"enAvailable":false},{"id":"jtp-13","setIdJa":"jtp","nameJa":"ネモ","nameEn":"Nemona","types":[],"imageJa":"images/sets/jtp/jp/154.jpg","imageEn":null,"enAvailable":false},{"id":"jtp-14","setIdJa":"jtp","nameJa":"タイカイデンex","nameEn":"Kilowattrel ex","types":["Lightning"],"imageJa":"images/sets/jtp/jp/155.jpg","imageEn":null,"enAvailable":false},{"id":"jtp-15","setIdJa":"jtp","nameJa":"ズルッグ","nameEn":"Scraggy","types":["Darkness"],"imageJa":"images/sets/jtp/jp/157.jpg","imageEn":null,"enAvailable":false},{"id":"jtp-16","setIdJa":"jtp","nameJa":"ズルズキン","nameEn":"Scrafty","types":["Darkness"],"imageJa":"images/sets/jtp/jp/158.jpg","imageEn":null,"enAvailable":false},{"id":"jtp-17","setIdJa":"jtp","nameJa":"ロトムスティック","nameEn":"Roto-Stick","types":[],"imageJa":"images/sets/jtp/jp/160.jpg","imageEn":null,"enAvailable":false},{"id":"jtp-18","setIdJa":"jtp","nameJa":"ヤンヤンマ","nameEn":"Yanma","types":["Grass"],"imageJa":"images/sets/jtp/jp/163.jpg","imageEn":null,"enAvailable":false},{"id":"jtp-19","setIdJa":"jtp","nameJa":"メガヤンマ","nameEn":"Yanmega","types":["Grass"],"imageJa":"images/sets/jtp/jp/164.jpg","imageEn":null,"enAvailable":false},{"id":"jtp-20","setIdJa":"jtp","nameJa":"ミガルーサex","nameEn":"Veluza ex","types":["Water"],"imageJa":"images/sets/jtp/jp/165.jpg","imageEn":null,"enAvailable":false},{"id":"jtp-21","setIdJa":"jtp","nameJa":"ビリー & オナレ","nameEn":"Billy & O'Nare","types":[],"imageJa":"images/sets/jtp/jp/170.jpg","imageEn":null,"enAvailable":false},{"id":"jtp-22","setIdJa":"jtp","nameJa":"ゼイユ","nameEn":"Carmine","types":[],"imageJa":"images/sets/jtp/jp/171.jpg","imageEn":null,"enAvailable":false},{"id":"jtp-23","setIdJa":"jtp","nameJa":"ヨルノズク","nameEn":"Noctowl","types":["Colorless"],"imageJa":"images/sets/jtp/jp/173.jpg","imageEn":null,"enAvailable":false},{"id":"jtp-24","setIdJa":"jtp","nameJa":"おいわいファンファーレ","nameEn":"Celebratory Fanfare","types":[],"imageJa":"images/sets/jtp/jp/174.jpg","imageEn":null,"enAvailable":false},{"id":"jtp-25","setIdJa":"jtp","nameJa":"アローラ ナッシーex","nameEn":"Alolan Exeggutor ex","types":["Grass"],"imageJa":"images/sets/jtp/jp/183.jpg","imageEn":null,"enAvailable":false},{"id":"jtp-26","setIdJa":"jtp","nameJa":"ベラカスex","nameEn":"Rabsca ex","types":["Grass"],"imageJa":"images/sets/jtp/jp/184.jpg","imageEn":null,"enAvailable":false},{"id":"jtp-27","setIdJa":"jtp","nameJa":"ヒポポタス","nameEn":"Hippopotas","types":["Fighting"],"imageJa":"images/sets/jtp/jp/186.jpg","imageEn":null,"enAvailable":false},{"id":"jtp-28","setIdJa":"jtp","nameJa":"カバルドン","nameEn":"Hippowdon","types":["Fighting"],"imageJa":"images/sets/jtp/jp/187.jpg","imageEn":null,"enAvailable":false},{"id":"jtp-29","setIdJa":"jtp","nameJa":"わざマシン","nameEn":"TM Machine","types":[],"imageJa":"images/sets/jtp/jp/189.jpg","imageEn":null,"enAvailable":false},{"id":"jtp-30","setIdJa":"jtp","nameJa":"アカマツ","nameEn":"Crispin","types":[],"imageJa":"images/sets/jtp/jp/191.jpg","imageEn":null,"enAvailable":false},{"id":"jtp-31","setIdJa":"jtp","nameJa":"イーブイ","nameEn":"Eevee","types":["Colorless"],"imageJa":"images/sets/jtp/jp/196.jpg","imageEn":null,"enAvailable":false},{"id":"jtp-32","setIdJa":"jtp","nameJa":"ピカチュウ","nameEn":"Pikachu","types":["Lightning"],"imageJa":"images/sets/jtp/jp/197.jpg","imageEn":null,"enAvailable":false},{"id":"jtp-33","setIdJa":"jtp","nameJa":"イーブイ","nameEn":"Eevee","types":["Colorless"],"imageJa":"images/sets/jtp/jp/198.jpg","imageEn":null,"enAvailable":false},{"id":"jtp-34","setIdJa":"jtp","nameJa":"シャリタツ","nameEn":"Tatsugiri","types":["Dragon"],"imageJa":"images/sets/jtp/jp/201.jpg","imageEn":null,"enAvailable":false},{"id":"jtp-35","setIdJa":"jtp","nameJa":"ハッサムex","nameEn":"Scizor ex","types":["Metal"],"imageJa":"images/sets/jtp/jp/210.jpg","imageEn":null,"enAvailable":false},{"id":"jtp-36","setIdJa":"jtp","nameJa":"改造ハンマー","nameEn":"Enhanced Hammer","types":[],"imageJa":"images/sets/jtp/jp/211.jpg","imageEn":null,"enAvailable":false},{"id":"jtp-37","setIdJa":"jtp","nameJa":"カイ","nameEn":"Irida","types":[],"imageJa":"images/sets/jtp/jp/219.jpg","imageEn":null,"enAvailable":false},{"id":"jtp-38","setIdJa":"jtp","nameJa":"ホップのバチンウニex","nameEn":"Hop's Pincurchin ex","types":["Lightning"],"imageJa":"images/sets/jtp/jp/233.jpg","imageEn":null,"enAvailable":false},{"id":"jtp-39","setIdJa":"jtp","nameJa":"フワンテ","nameEn":"Drifloon","types":["Psychic"],"imageJa":"images/sets/jtp/jp/234.jpg","imageEn":null,"enAvailable":false},{"id":"jtp-40","setIdJa":"jtp","nameJa":"フワライド","nameEn":"Drifblim","types":["Psychic"],"imageJa":"images/sets/jtp/jp/235.jpg","imageEn":null,"enAvailable":false},{"id":"jtp-41","setIdJa":"jtp","nameJa":"シャリタツ","nameEn":"Tatsugiri","types":["Dragon"],"imageJa":"images/sets/jtp/jp/236.jpg","imageEn":null,"enAvailable":false},{"id":"jtp-42","setIdJa":"jtp","nameJa":"なかよしポフィン","nameEn":"Buddy-Buddy Poffin","types":[],"imageJa":"images/sets/jtp/jp/237.jpg","imageEn":null,"enAvailable":false},{"id":"jtp-43","setIdJa":"jtp","nameJa":"ペパー","nameEn":"Arven","types":[],"imageJa":"images/sets/jtp/jp/238.jpg","imageEn":null,"enAvailable":false},{"id":"jtp-44","setIdJa":"jtp","nameJa":"ポケモンセンターのお姉さん","nameEn":"Pokémon Center Lady","types":[],"imageJa":"images/sets/jtp/jp/239.jpg","imageEn":null,"enAvailable":false},{"id":"jtp-45","setIdJa":"jtp","nameJa":"カキツバタ","nameEn":"Drayton","types":[],"imageJa":"images/sets/jtp/jp/240.jpg","imageEn":null,"enAvailable":false},{"id":"jtp-46","setIdJa":"jtp","nameJa":"なかよしポフィン","nameEn":"Buddy-Buddy Poffin","types":[],"imageJa":"images/sets/jtp/jp/244.jpg","imageEn":null,"enAvailable":false},{"id":"jtp-47","setIdJa":"jtp","nameJa":"ハイパーボール","nameEn":"Ultra Ball","types":[],"imageJa":"images/sets/jtp/jp/245.jpg","imageEn":null,"enAvailable":false},{"id":"jtp-48","setIdJa":"jtp","nameJa":"ふしぎなアメ","nameEn":"Rare Candy","types":[],"imageJa":"images/sets/jtp/jp/246.jpg","imageEn":null,"enAvailable":false},{"id":"jtp-49","setIdJa":"jtp","nameJa":"ポケギア3.0","nameEn":"Poké Gear 3.0","types":[],"imageJa":"images/sets/jtp/jp/247.jpg","imageEn":null,"enAvailable":false},{"id":"jtp-50","setIdJa":"jtp","nameJa":"ポケモンいれかえ","nameEn":"Switch","types":[],"imageJa":"images/sets/jtp/jp/248.jpg","imageEn":null,"enAvailable":false},{"id":"jtp-51","setIdJa":"jtp","nameJa":"からておうの指令","nameEn":"Black Belt's Training","types":[],"imageJa":"images/sets/jtp/jp/249.jpg","imageEn":null,"enAvailable":false},{"id":"jtp-52","setIdJa":"jtp","nameJa":"ポケモンセンターのお姉さん","nameEn":"Pokémon Center Lady","types":[],"imageJa":"images/sets/jtp/jp/250.jpg","imageEn":null,"enAvailable":false},{"id":"jtp-53","setIdJa":"jtp","nameJa":"エキサイトスタジアム","nameEn":"Lively Stadium","types":[],"imageJa":"images/sets/jtp/jp/251.jpg","imageEn":null,"enAvailable":false},{"id":"jtp-54","setIdJa":"jtp","nameJa":"ネモ","nameEn":"Nemona","types":[],"imageJa":"images/sets/jtp/jp/252.jpg","imageEn":null,"enAvailable":false},{"id":"jtp-55","setIdJa":"jtp","nameJa":"ネモ","nameEn":"Nemona","types":[],"imageJa":"images/sets/jtp/jp/253.jpg","imageEn":null,"enAvailable":false},{"id":"jtp-56","setIdJa":"jtp","nameJa":"ヒビキのホウオウex","nameEn":"Ethan's Ho-Oh ex","types":["Fire"],"imageJa":"images/sets/jtp/jp/254.jpg","imageEn":null,"enAvailable":false},{"id":"jtp-57","setIdJa":"jtp","nameJa":"シロナのガブリアスex","nameEn":"Cynthia's Garchomp ex","types":["Fighting"],"imageJa":"images/sets/jtp/jp/255.jpg","imageEn":null,"enAvailable":false},{"id":"jtp-58","setIdJa":"jtp","nameJa":"ペパーのマフィティフex","nameEn":"Arven's Mabosstiff ex","types":["Darkness"],"imageJa":"images/sets/jtp/jp/256.jpg","imageEn":null,"enAvailable":false},{"id":"jtp-59","setIdJa":"jtp","nameJa":"ガチグマアカツキex","nameEn":"Bloodmoon Ursaluna ex","types":["Colorless"],"imageJa":"images/sets/jtp/jp/258.jpg","imageEn":null,"enAvailable":false},{"id":"jtp-60","setIdJa":"jtp","nameJa":"コダック","nameEn":"Psyduck","types":["Water"],"imageJa":"images/sets/jtp/jp/262.jpg","imageEn":null,"enAvailable":false},{"id":"jtp-61","setIdJa":"jtp","nameJa":"ゴルダック","nameEn":"Golduck","types":["Water"],"imageJa":"images/sets/jtp/jp/263.jpg","imageEn":null,"enAvailable":false},{"id":"jtp-62","setIdJa":"jtp","nameJa":"ハバタクカミ","nameEn":"Flutter Mane","types":["Psychic"],"imageJa":"images/sets/jtp/jp/264.jpg","imageEn":null,"enAvailable":false},{"id":"jtp-63","setIdJa":"jtp","nameJa":"ロケット団のガルーラex","nameEn":"Team Rocket's Kangaskhan ex","types":["Colorless"],"imageJa":"images/sets/jtp/jp/265.jpg","imageEn":null,"enAvailable":false},{"id":"jtp-64","setIdJa":"jtp","nameJa":"夜のタンカ","nameEn":"Night Stretcher","types":[],"imageJa":"images/sets/jtp/jp/266.jpg","imageEn":null,"enAvailable":false},{"id":"jtp-65","setIdJa":"jtp","nameJa":"ロケット団の催眠装置","nameEn":"Team Rocket's Hypnosis Device","types":[],"imageJa":"images/sets/jtp/jp/267.jpg","imageEn":null,"enAvailable":false},{"id":"jtp-66","setIdJa":"jtp","nameJa":"スグリ","nameEn":"Kieran","types":[],"imageJa":"images/sets/jtp/jp/268.jpg","imageEn":null,"enAvailable":false},{"id":"jtp-67","setIdJa":"jtp","nameJa":"アイリスの闘志","nameEn":"Iris's Fighting Spirit","types":[],"imageJa":"images/sets/jtp/jp/269.jpg","imageEn":null,"enAvailable":false},{"id":"jtp-68","setIdJa":"jtp","nameJa":"ビクティニ","nameEn":"Victini","types":["Fire"],"imageJa":"images/sets/jtp/jp/288.jpg","imageEn":null,"enAvailable":false},{"id":"jtp-69","setIdJa":"jtp","nameJa":"ピカチュウ","nameEn":"Pikachu","types":["Lightning"],"imageJa":"images/sets/jtp/jp/291.jpg","imageEn":null,"enAvailable":false}]