[{"id":"md-1","setIdJa":"md","nameJa":"ヒビキのカイロス","nameEn":"Ethan's Pinsir","supertype":"Pokémon","subtypes":["Basic"],"types":["Grass"],"regulationMark":"I","imageJa":"images/sets/md/jp/1.jpg","imageEn":"images/sets/md/en/1.jpg","enAvailable":true},{"id":"md-2","setIdJa":"md","nameJa":"ヤンヤンマ","nameEn":"Yanma","supertype":"Pokémon","subtypes":["Basic"],"types":["Grass"],"regulationMark":"I","imageJa":"images/sets/md/jp/2.jpg","imageEn":"images/sets/md/en/2.jpg","enAvailable":true},{"id":"md-3","setIdJa":"md","nameJa":"メガヤンマex","nameEn":"Yanmega ex","supertype":"Pokémon","subtypes":["Stage 1","ex"],"types":["Grass"],"regulationMark":"I","imageJa":"images/sets/md/jp/3.jpg","imageEn":"images/sets/md/en/3.jpg","enAvailable":true},{"id":"md-4","setIdJa":"md","nameJa":"ケムッソ","nameEn":"Wurmple","supertype":"Pokémon","subtypes":["Basic"],"types":["Grass"],"regulationMark":"I","imageJa":"images/sets/md/jp/4.jpg","imageEn":"images/sets/md/en/4.jpg","enAvailable":true},{"id":"md-5","setIdJa":"md","nameJa":"カラサリス","nameEn":"Silcoon","supertype":"Pokémon","subtypes":["Stage 1"],"types":["Grass"],"regulationMark":"I","imageJa":"images/sets/md/jp/5.jpg","imageEn":"images/sets/md/en/5.jpg","enAvailable":true},{"id":"md-6","setIdJa":"md","nameJa":"アゲハント","nameEn":"Beautifly","supertype":"Pokémon","subtypes":["Stage 2"],"types":["Grass"],"regulationMark":"I","imageJa":"images/sets/md/jp/6.jpg","imageEn":"images/sets/md/en/6.jpg","enAvailable":true},{"id":"md-7","setIdJa":"md","nameJa":"マユルド","nameEn":"Cascoon","supertype":"Pokémon","subtypes":["Stage 1"],"types":["Grass"],"regulationMark":"I","imageJa":"images/sets/md/jp/7.jpg","imageEn":"images/sets/md/en/7.jpg","enAvailable":true},{"id":"md-8","setIdJa":"md","nameJa":"ドクケイル","nameEn":"Dustox","supertype":"Pokémon","subtypes":["Stage 2"],"types":["Grass"],"regulationMark":"I","imageJa":"images/sets/md/jp/8.jpg","imageEn":"images/sets/md/en/8.jpg","enAvailable":true},{"id":"md-9","setIdJa":"md","nameJa":"シロナのロゼリア","nameEn":"Cynthia's Roselia","supertype":"Pokémon","subtypes":["Basic"],"types":["Grass"],"regulationMark":"I","imageJa":"images/sets/md/jp/9.jpg","imageEn":"images/sets/md/en/9.jpg","enAvailable":true},{"id":"md-10","setIdJa":"md","nameJa":"シロナのロズレイド","nameEn":"Cynthia's Roserade","supertype":"Pokémon","subtypes":["Stage 1"],"types":["Grass"],"regulationMark":"I","imageJa":"images/sets/md/jp/10.jpg","imageEn":"images/sets/md/en/10.jpg","enAvailable":true},{"id":"md-11","setIdJa":"md","nameJa":"スボミー","nameEn":"Budew","supertype":"Pokémon","subtypes":["Basic"],"types":["Grass"],"regulationMark":"H","imageJa":"images/sets/md/jp/11.jpg","imageEn":"images/sets/md/en/11.jpg","enAvailable":true},{"id":"md-12","setIdJa":"md","nameJa":"シェイミ","nameEn":"Shaymin","supertype":"Pokémon","subtypes":["Basic"],"types":["Grass"],"regulationMark":"I","imageJa":"images/sets/md/jp/12.jpg","imageEn":"images/sets/md/en/12.jpg","enAvailable":true},{"id":"md-13","setIdJa":"md","nameJa":"イシズマイ","nameEn":"Dwebble","supertype":"Pokémon","subtypes":["Basic"],"types":["Grass"],"regulationMark":"I","imageJa":"images/sets/md/jp/13.jpg","imageEn":"images/sets/md/en/13.jpg","enAvailable":true},{"id":"md-14","setIdJa":"md","nameJa":"イワパレス","nameEn":"Crustle","supertype":"Pokémon","subtypes":["Stage 1"],"types":["Grass"],"regulationMark":"I","imageJa":"images/sets/md/jp/14.jpg","imageEn":"images/sets/md/en/14.jpg","enAvailable":true},{"id":"md-15","setIdJa":"md","nameJa":"ロケット団のタマンチュラ","nameEn":"Team Rocket's Tarountula","supertype":"Pokémon","subtypes":["Basic"],"types":["Grass"],"regulationMark":"I","imageJa":"images/sets/md/jp/15.jpg","imageEn":"images/sets/md/en/15.jpg","enAvailable":true},{"id":"md-16","setIdJa":"md","nameJa":"ロケット団のワナイダー","nameEn":"Team Rocket's Spidops","supertype":"Pokémon","subtypes":["Stage 1"],"types":["Grass"],"regulationMark":"I","imageJa":"images/sets/md/jp/16.jpg","imageEn":"images/sets/md/en/16.jpg","enAvailable":true},{"id":"md-17","setIdJa":"md","nameJa":"オーガポンみどりのめんex","nameEn":"Teal Mask Ogerpon ex","supertype":"Pokémon","subtypes":["Basic","Tera","ex"],"types":["Grass"],"regulationMark":"H","imageJa":"images/sets/md/jp/17.jpg","imageEn":"images/sets/md/en/17.jpg","enAvailable":true},{"id":"md-18","setIdJa":"md","nameJa":"ヒビキのマグマッグ","nameEn":"Ethan's Slugma","supertype":"Pokémon","subtypes":["Basic"],"types":["Fire"],"regulationMark":"I","imageJa":"images/sets/md/jp/18.jpg","imageEn":"images/sets/md/en/18.jpg","enAvailable":true},{"id":"md-19","setIdJa":"md","nameJa":"ヒビキのマグカルゴ","nameEn":"Ethan's Magcargo","supertype":"Pokémon","subtypes":["Stage 1"],"types":["Fire"],"regulationMark":"I","imageJa":"images/sets/md/jp/19.jpg","imageEn":"images/sets/md/en/19.jpg","enAvailable":true},{"id":"md-20","setIdJa":"md","nameJa":"エンテイ","nameEn":"Entei","supertype":"Pokémon","subtypes":["Basic"],"types":["Fire"],"regulationMark":"I","imageJa":"images/sets/md/jp/20.jpg","imageEn":"images/sets/md/en/20.jpg","enAvailable":true},{"id":"md-21","setIdJa":"md","nameJa":"ヒビキのホウオウex","nameEn":"Ethan's Ho-Oh ex","supertype":"Pokémon","subtypes":["Basic","ex"],"types":["Fire"],"regulationMark":"I","imageJa":"images/sets/md/jp/21.jpg","imageEn":"images/sets/md/en/21.jpg","enAvailable":true},{"id":"md-22","setIdJa":"md","nameJa":"ドンメル","nameEn":"Numel","supertype":"Pokémon","subtypes":["Basic"],"types":["Fire"],"regulationMark":"I","imageJa":"images/sets/md/jp/22.jpg","imageEn":"images/sets/md/en/22.jpg","enAvailable":true},{"id":"md-23","setIdJa":"md","nameJa":"バクーダ","nameEn":"Camerupt","supertype":"Pokémon","subtypes":["Stage 1"],"types":["Fire"],"regulationMark":"I","imageJa":"images/sets/md/jp/23.jpg","imageEn":"images/sets/md/en/23.jpg","enAvailable":true},{"id":"md-24","setIdJa":"md","nameJa":"ポカブ","nameEn":"Tepig","supertype":"Pokémon","subtypes":["Basic"],"types":["Fire"],"regulationMark":"I","imageJa":"images/sets/md/jp/24.jpg","imageEn":"images/sets/md/en/24.jpg","enAvailable":true},{"id":"md-25","setIdJa":"md","nameJa":"チャオブー","nameEn":"Pignite","supertype":"Pokémon","subtypes":["Stage 1"],"types":["Fire"],"regulationMark":"I","imageJa":"images/sets/md/jp/25.jpg","imageEn":"images/sets/md/en/25.jpg","enAvailable":true},{"id":"md-26","setIdJa":"md","nameJa":"エンブオー","nameEn":"Emboar","supertype":"Pokémon","subtypes":["Stage 2"],"types":["Fire"],"regulationMark":"I","imageJa":"images/sets/md/jp/26.jpg","imageEn":"images/sets/md/en/26.jpg","enAvailable":true},{"id":"md-27","setIdJa":"md","nameJa":"Nのダルマッカ","nameEn":"N's Darumaka","supertype":"Pokémon","subtypes":["Basic"],"types":["Fire"],"regulationMark":"I","imageJa":"images/sets/md/jp/27.jpg","imageEn":"images/sets/md/en/27.jpg","enAvailable":true},{"id":"md-28","setIdJa":"md","nameJa":"Nのヒヒダルマ","nameEn":"N's Darmanitan","supertype":"Pokémon","subtypes":["Stage 1"],"types":["Fire"],"regulationMark":"I","imageJa":"images/sets/md/jp/28.jpg","imageEn":"images/sets/md/en/28.jpg","enAvailable":true},{"id":"md-29","setIdJa":"md","nameJa":"レシラムex","nameEn":"Reshiram ex","supertype":"Pokémon","subtypes":["Basic","ex"],"types":["Fire"],"regulationMark":"I","imageJa":"images/sets/md/jp/29.jpg","imageEn":"images/sets/md/en/29.jpg","enAvailable":true},{"id":"md-30","setIdJa":"md","nameJa":"カルボウ","nameEn":"Charcadet","supertype":"Pokémon","subtypes":["Basic"],"types":["Fire"],"regulationMark":"H","imageJa":"images/sets/md/jp/30.jpg","imageEn":"images/sets/md/en/30.jpg","enAvailable":true},{"id":"md-31","setIdJa":"md","nameJa":"ソウブレイズex","nameEn":"Ceruledge ex","supertype":"Pokémon","subtypes":["Stage 1","Tera","ex"],"types":["Fire"],"regulationMark":"H","imageJa":"images/sets/md/jp/31.jpg","imageEn":"images/sets/md/en/31.jpg","enAvailable":true},{"id":"md-32","setIdJa":"md","nameJa":"コダック","nameEn":"Psyduck","supertype":"Pokémon","subtypes":["Basic"],"types":["Water"],"regulationMark":"I","imageJa":"images/sets/md/jp/32.jpg","imageEn":"images/sets/md/en/32.jpg","enAvailable":true},{"id":"md-33","setIdJa":"md","nameJa":"ゴルダック","nameEn":"Golduck","supertype":"Pokémon","subtypes":["Stage 1"],"types":["Water"],"regulationMark":"I","imageJa":"images/sets/md/jp/33.jpg","imageEn":"images/sets/md/en/33.jpg","enAvailable":true},{"id":"md-34","setIdJa":"md","nameJa":"ロケット団のフリーザー","nameEn":"Team Rocket's Articuno","supertype":"Pokémon","subtypes":["Basic"],"types":["Water"],"regulationMark":"I","imageJa":"images/sets/md/jp/34.jpg","imageEn":"images/sets/md/en/34.jpg","enAvailable":true},{"id":"md-35","setIdJa":"md","nameJa":"ユキワラシ","nameEn":"Snorunt","supertype":"Pokémon","subtypes":["Basic"],"types":["Water"],"regulationMark":"I","imageJa":"images/sets/md/jp/35.jpg","imageEn":"images/sets/md/en/35.jpg","enAvailable":true},{"id":"md-36","setIdJa":"md","nameJa":"メガユキメノコex","nameEn":"Mega Froslass ex","supertype":"Pokémon","subtypes":["Stage 1","MEGA","ex"],"types":["Water"],"regulationMark":"I","imageJa":"images/sets/md/jp/36.jpg","imageEn":"images/sets/md/en/36.jpg","enAvailable":true},{"id":"md-37","setIdJa":"md","nameJa":"Nのバニプッチ","nameEn":"N's Vanillite","supertype":"Pokémon","subtypes":["Basic"],"types":["Water"],"regulationMark":"I","imageJa":"images/sets/md/jp/37.jpg","imageEn":"images/sets/md/en/37.jpg","enAvailable":true},{"id":"md-38","setIdJa":"md","nameJa":"Nのバニリッチ","nameEn":"N's Vanillish","supertype":"Pokémon","subtypes":["Stage 1"],"types":["Water"],"regulationMark":"I","imageJa":"images/sets/md/jp/38.jpg","imageEn":"images/sets/md/en/38.jpg","enAvailable":true},{"id":"md-39","setIdJa":"md","nameJa":"Nのバイバニラ","nameEn":"N's Vanilluxe","supertype":"Pokémon","subtypes":["Stage 2"],"types":["Water"],"regulationMark":"I","imageJa":"images/sets/md/jp/39.jpg","imageEn":"images/sets/md/en/39.jpg","enAvailable":true},{"id":"md-40","setIdJa":"md","nameJa":"ユキハミ","nameEn":"Snom","supertype":"Pokémon","subtypes":["Basic"],"types":["Water"],"regulationMark":"I","imageJa":"images/sets/md/jp/40.jpg","imageEn":"images/sets/md/en/40.jpg","enAvailable":true},{"id":"md-41","setIdJa":"md","nameJa":"モスノウ","nameEn":"Frosmoth","supertype":"Pokémon","subtypes":["Stage 1"],"types":["Water"],"regulationMark":"I","imageJa":"images/sets/md/jp/41.jpg","imageEn":"images/sets/md/en/41.jpg","enAvailable":true},{"id":"md-42","setIdJa":"md","nameJa":"ブリザポス","nameEn":"Glastrier","supertype":"Pokémon","subtypes":["Basic"],"types":["Water"],"regulationMark":"I","imageJa":"images/sets/md/jp/42.jpg","imageEn":"images/sets/md/en/42.jpg","enAvailable":true},{"id":"md-43","setIdJa":"md","nameJa":"パオジアン","nameEn":"Chien-Pao","supertype":"Pokémon","subtypes":["Basic"],"types":["Water"],"regulationMark":"H","imageJa":"images/sets/md/jp/43.jpg","imageEn":"images/sets/md/en/43.jpg","enAvailable":true},{"id":"md-44","setIdJa":"md","nameJa":"ピカチュウex","nameEn":"Pikachu ex","supertype":"Pokémon","subtypes":["Basic","Tera","ex"],"types":["Lightning"],"regulationMark":"H","imageJa":"images/sets/md/jp/44.jpg","imageEn":"images/sets/md/en/44.jpg","enAvailable":true},{"id":"md-45","setIdJa":"md","nameJa":"コイル","nameEn":"Magnemite","supertype":"Pokémon","subtypes":["Basic"],"types":["Lightning"],"regulationMark":"H","imageJa":"images/sets/md/jp/45.jpg","imageEn":"images/sets/md/en/45.jpg","enAvailable":true},{"id":"md-46","setIdJa":"md","nameJa":"レアコイル","nameEn":"Magneton","supertype":"Pokémon","subtypes":["Stage 1"],"types":["Lightning"],"regulationMark":"H","imageJa":"images/sets/md/jp/46.jpg","imageEn":"images/sets/md/en/46.jpg","enAvailable":true},{"id":"md-47","setIdJa":"md","nameJa":"シビシラス","nameEn":"Tynamo","supertype":"Pokémon","subtypes":["Basic"],"types":["Lightning"],"regulationMark":"I","imageJa":"images/sets/md/jp/47.jpg","imageEn":"images/sets/md/en/47.jpg","enAvailable":true},{"id":"md-48","setIdJa":"md","nameJa":"シビビール","nameEn":"Eelektrik","supertype":"Pokémon","subtypes":["Stage 1"],"types":["Lightning"],"regulationMark":"I","imageJa":"images/sets/md/jp/48.jpg","imageEn":"images/sets/md/en/48.jpg","enAvailable":true},{"id":"md-49","setIdJa":"md","nameJa":"メガシビルドンex","nameEn":"Mega Eelektross ex","supertype":"Pokémon","subtypes":["Stage 2","MEGA","ex"],"types":["Lightning"],"regulationMark":"I","imageJa":"images/sets/md/jp/49.jpg","imageEn":"images/sets/md/en/49.jpg","enAvailable":true},{"id":"md-50","setIdJa":"md","nameJa":"マッギョ","nameEn":"Stunfisk","supertype":"Pokémon","subtypes":["Basic"],"types":["Lightning"],"regulationMark":"I","imageJa":"images/sets/md/jp/50.jpg","imageEn":"images/sets/md/en/50.jpg","enAvailable":true},{"id":"md-51","setIdJa":"md","nameJa":"ゼクロムex","nameEn":"Zekrom ex","supertype":"Pokémon","subtypes":["Basic","ex"],"types":["Lightning"],"regulationMark":"I","imageJa":"images/sets/md/jp/51.jpg","imageEn":"images/sets/md/en/51.jpg","enAvailable":true},{"id":"md-52","setIdJa":"md","nameJa":"エリキテル","nameEn":"Helioptile","supertype":"Pokémon","subtypes":["Basic"],"types":["Lightning"],"regulationMark":"I","imageJa":"images/sets/md/jp/52.jpg","imageEn":"images/sets/md/en/52.jpg","enAvailable":true},{"id":"md-53","setIdJa":"md","nameJa":"エレザード","nameEn":"Heliolisk","supertype":"Pokémon","subtypes":["Stage 1"],"types":["Lightning"],"regulationMark":"I","imageJa":"images/sets/md/jp/53.jpg","imageEn":"images/sets/md/en/53.jpg","enAvailable":true},{"id":"md-54","setIdJa":"md","nameJa":"カプ・コケコ","nameEn":"Tapu Koko","supertype":"Pokémon","subtypes":["Basic"],"types":["Lightning"],"regulationMark":"I","imageJa":"images/sets/md/jp/54.jpg","imageEn":"images/sets/md/en/54.jpg","enAvailable":true},{"id":"md-55","setIdJa":"md","nameJa":"ゼラオラ","nameEn":"Zeraora","supertype":"Pokémon","subtypes":["Basic"],"types":["Lightning"],"regulationMark":"I","imageJa":"images/sets/md/jp/55.jpg","imageEn":"images/sets/md/en/55.jpg","enAvailable":true},{"id":"md-56","setIdJa":"md","nameJa":"ナンジャモのズピカ","nameEn":"Iono's Tadbulb","supertype":"Pokémon","subtypes":["Basic"],"types":["Lightning"],"regulationMark":"I","imageJa":"images/sets/md/jp/56.jpg","imageEn":"images/sets/md/en/56.jpg","enAvailable":true},{"id":"md-57","setIdJa":"md","nameJa":"ナンジャモのハラバリーex","nameEn":"Iono's Bellibolt ex","supertype":"Pokémon","subtypes":["Stage 1","ex"],"types":["Lightning"],"regulationMark":"I","imageJa":"images/sets/md/jp/57.jpg","imageEn":"images/sets/md/en/57.jpg","enAvailable":true},{"id":"md-58","setIdJa":"md","nameJa":"ナンジャモのカイデン","nameEn":"Iono's Wattrel","supertype":"Pokémon","subtypes":["Basic"],"types":["Lightning"],"regulationMark":"I","imageJa":"images/sets/md/jp/58.jpg","imageEn":"images/sets/md/en/58.jpg","enAvailable":true},{"id":"md-59","setIdJa":"md","nameJa":"ナンジャモのタイカイデン","nameEn":"Iono's Kilowattrel","supertype":"Pokémon","subtypes":["Stage 1"],"types":["Lightning"],"regulationMark":"I","imageJa":"images/sets/md/jp/59.jpg","imageEn":"images/sets/md/en/59.jpg","enAvailable":true},{"id":"md-60","setIdJa":"md","nameJa":"リーリエのピッピex","nameEn":"Lillie's Clefairy ex","supertype":"Pokémon","subtypes":["Basic","ex"],"types":["Psychic"],"regulationMark":"I","imageJa":"images/sets/md/jp/60.jpg","imageEn":"images/sets/md/en/60.jpg","enAvailable":true},{"id":"md-61","setIdJa":"md","nameJa":"ロケット団のタマタマ","nameEn":"Team Rocket's Exeggcute","supertype":"Pokémon","subtypes":["Basic"],"types":["Psychic"],"regulationMark":"I","imageJa":"images/sets/md/jp/61.jpg","imageEn":"images/sets/md/en/61.jpg","enAvailable":true},{"id":"md-62","setIdJa":"md","nameJa":"ロケット団のナッシー","nameEn":"Team Rocket's Exeggutor","supertype":"Pokémon","subtypes":["Stage 1"],"types":["Psychic"],"regulationMark":"I","imageJa":"images/sets/md/jp/62.jpg","imageEn":"images/sets/md/en/62.jpg","enAvailable":true},{"id":"md-63","setIdJa":"md","nameJa":"ロケット団のミュウツーex","nameEn":"Team Rocket's Mewtwo ex","supertype":"Pokémon","subtypes":["Basic","ex"],"types":["Psychic"],"regulationMark":"I","imageJa":"images/sets/md/jp/63.jpg","imageEn":"images/sets/md/en/63.jpg","enAvailable":true},{"id":"md-64","setIdJa":"md","nameJa":"トゲピー","nameEn":"Togepi","supertype":"Pokémon","subtypes":["Basic"],"types":["Psychic"],"regulationMark":"H","imageJa":"images/sets/md/jp/64.jpg","imageEn":"images/sets/md/en/64.jpg","enAvailable":true},{"id":"md-65","setIdJa":"md","nameJa":"トゲチック","nameEn":"Togetic","supertype":"Pokémon","subtypes":["Stage 1"],"types":["Psychic"],"regulationMark":"H","imageJa":"images/sets/md/jp/65.jpg","imageEn":"images/sets/md/en/65.jpg","enAvailable":true},{"id":"md-66","setIdJa":"md","nameJa":"トゲキッス","nameEn":"Togekiss","supertype":"Pokémon","subtypes":["Stage 2"],"types":["Psychic"],"regulationMark":"H","imageJa":"images/sets/md/jp/66.jpg","imageEn":"images/sets/md/en/66.jpg","enAvailable":true},{"id":"md-67","setIdJa":"md","nameJa":"ムウマ","nameEn":"Misdreavus","supertype":"Pokémon","subtypes":["Basic"],"types":["Psychic"],"regulationMark":"I","imageJa":"images/sets/md/jp/67.jpg","imageEn":"images/sets/md/en/67.jpg","enAvailable":true},{"id":"md-68","setIdJa":"md","nameJa":"ムウマージ","nameEn":"Mismagius","supertype":"Pokémon","subtypes":["Stage 1"],"types":["Psychic"],"regulationMark":"I","imageJa":"images/sets/md/jp/68.jpg","imageEn":"images/sets/md/en/68.jpg","enAvailable":true},{"id":"md-69","setIdJa":"md","nameJa":"ラルトス","nameEn":"Ralts","supertype":"Pokémon","subtypes":["Basic"],"types":["Psychic"],"regulationMark":"I","imageJa":"images/sets/md/jp/69.jpg","imageEn":"images/sets/md/en/69.jpg","enAvailable":true},{"id":"md-70","setIdJa":"md","nameJa":"キルリア","nameEn":"Kirlia","supertype":"Pokémon","subtypes":["Stage 1"],"types":["Psychic"],"regulationMark":"I","imageJa":"images/sets/md/jp/70.jpg","imageEn":"images/sets/md/en/70.jpg","enAvailable":true},{"id":"md-71","setIdJa":"md","nameJa":"メガサーナイトex","nameEn":"Mega Gardevoir ex","supertype":"Pokémon","subtypes":["Stage 2","MEGA","ex"],"types":["Psychic"],"regulationMark":"I","imageJa":"images/sets/md/jp/71.jpg","imageEn":"images/sets/md/en/71.jpg","enAvailable":true},{"id":"md-72","setIdJa":"md","nameJa":"ヨマワル","nameEn":"Duskull","supertype":"Pokémon","subtypes":["Basic"],"types":["Psychic"],"regulationMark":"H","imageJa":"images/sets/md/jp/72.jpg","imageEn":"images/sets/md/en/72.jpg","enAvailable":true},{"id":"md-73","setIdJa":"md","nameJa":"サマヨール","nameEn":"Dusclops","supertype":"Pokémon","subtypes":["Stage 1"],"types":["Psychic"],"regulationMark":"H","imageJa":"images/sets/md/jp/73.jpg","imageEn":"images/sets/md/en/73.jpg","enAvailable":true},{"id":"md-74","setIdJa":"md","nameJa":"ヨノワール","nameEn":"Dusknoir","supertype":"Pokémon","subtypes":["Stage 2"],"types":["Psychic"],"regulationMark":"H","imageJa":"images/sets/md/jp/74.jpg","imageEn":"images/sets/md/en/74.jpg","enAvailable":true},{"id":"md-75","setIdJa":"md","nameJa":"ラティアスex","nameEn":"Latias ex","supertype":"Pokémon","subtypes":["Basic","ex"],"types":["Psychic"],"regulationMark":"H","imageJa":"images/sets/md/jp/75.jpg","imageEn":"images/sets/md/en/75.jpg","enAvailable":true},{"id":"md-76","setIdJa":"md","nameJa":"ロトム","nameEn":"Rotom","supertype":"Pokémon","subtypes":["Basic"],"types":["Psychic"],"regulationMark":"I","imageJa":"images/sets/md/jp/76.jpg","imageEn":"images/sets/md/en/76.jpg","enAvailable":true},{"id":"md-77","setIdJa":"md","nameJa":"ホップのボクレー","nameEn":"Hop's Phantump","supertype":"Pokémon","subtypes":["Basic"],"types":["Psychic"],"regulationMark":"I","imageJa":"images/sets/md/jp/77.jpg","imageEn":"images/sets/md/en/77.jpg","enAvailable":true},{"id":"md-78","setIdJa":"md","nameJa":"ホップのオーロット","nameEn":"Hop's Trevenant","supertype":"Pokémon","subtypes":["Stage 1"],"types":["Psychic"],"regulationMark":"I","imageJa":"images/sets/md/jp/78.jpg","imageEn":"images/sets/md/en/78.jpg","enAvailable":true},{"id":"md-79","setIdJa":"md","nameJa":"ロケット団のミミッキュ","nameEn":"Team Rocket's Mimikyu","supertype":"Pokémon","subtypes":["Basic"],"types":["Psychic"],"regulationMark":"I","imageJa":"images/sets/md/jp/79.jpg","imageEn":"images/sets/md/en/79.jpg","enAvailable":true},{"id":"md-80","setIdJa":"md","nameJa":"レイスポス","nameEn":"Spectrier","supertype":"Pokémon","subtypes":["Basic"],"types":["Psychic"],"regulationMark":"I","imageJa":"images/sets/md/jp/80.jpg","imageEn":"images/sets/md/en/80.jpg","enAvailable":true},{"id":"md-81","setIdJa":"md","nameJa":"マシマシラ","nameEn":"Munkidori","supertype":"Pokémon","subtypes":["Basic"],"types":["Psychic"],"regulationMark":"H","imageJa":"images/sets/md/jp/81.jpg","imageEn":"images/sets/md/en/81.jpg","enAvailable":true},{"id":"md-82","setIdJa":"md","nameJa":"ロケット団のディグダ","nameEn":"Team Rocket's Diglett","supertype":"Pokémon","subtypes":["Basic"],"types":["Fighting"],"regulationMark":"I","imageJa":"images/sets/md/jp/82.jpg","imageEn":"images/sets/md/en/82.jpg","enAvailable":true},{"id":"md-83","setIdJa":"md","nameJa":"ロケット団のダグトリオ","nameEn":"Team Rocket's Dugtrio","supertype":"Pokémon","subtypes":["Stage 1"],"types":["Fighting"],"regulationMark":"I","imageJa":"images/sets/md/jp/83.jpg","imageEn":"images/sets/md/en/83.jpg","enAvailable":true},{"id":"md-84","setIdJa":"md","nameJa":"アサナン","nameEn":"Meditite","supertype":"Pokémon","subtypes":["Basic"],"types":["Fighting"],"regulationMark":"I","imageJa":"images/sets/md/jp/84.jpg","imageEn":"images/sets/md/en/84.jpg","enAvailable":true},{"id":"md-85","setIdJa":"md","nameJa":"チャーレム","nameEn":"Medicham","supertype":"Pokémon","subtypes":["Stage 1"],"types":["Fighting"],"regulationMark":"I","imageJa":"images/sets/md/jp/85.jpg","imageEn":"images/sets/md/en/85.jpg","enAvailable":true},{"id":"md-86","setIdJa":"md","nameJa":"ルナトーン","nameEn":"Lunatone","supertype":"Pokémon","subtypes":["Basic"],"types":["Fighting"],"regulationMark":"I","imageJa":"images/sets/md/jp/86.jpg","imageEn":"images/sets/md/en/86.jpg","enAvailable":true},{"id":"md-87","setIdJa":"md","nameJa":"ソルロック","nameEn":"Solrock","supertype":"Pokémon","subtypes":["Basic"],"types":["Fighting"],"regulationMark":"I","imageJa":"images/sets/md/jp/87.jpg","imageEn":"images/sets/md/en/87.jpg","enAvailable":true},{"id":"md-88","setIdJa":"md","nameJa":"シロナのフカマル","nameEn":"Cynthia's Gible","supertype":"Pokémon","subtypes":["Basic"],"types":["Fighting"],"regulationMark":"I","imageJa":"images/sets/md/jp/88.jpg","imageEn":"images/sets/md/en/88.jpg","enAvailable":true},{"id":"md-89","setIdJa":"md","nameJa":"シロナのガバイト","nameEn":"Cynthia's Gabite","supertype":"Pokémon","subtypes":["Stage 1"],"types":["Fighting"],"regulationMark":"I","imageJa":"images/sets/md/jp/89.jpg","imageEn":"images/sets/md/en/89.jpg","enAvailable":true},{"id":"md-90","setIdJa":"md","nameJa":"シロナのガブリアスex","nameEn":"Cynthia's Garchomp ex","supertype":"Pokémon","subtypes":["Stage 2","ex"],"types":["Fighting"],"regulationMark":"I","imageJa":"images/sets/md/jp/90.jpg","imageEn":"images/sets/md/en/90.jpg","enAvailable":true},{"id":"md-91","setIdJa":"md","nameJa":"リオル","nameEn":"Riolu","supertype":"Pokémon","subtypes":["Basic"],"types":["Fighting"],"regulationMark":"I","imageJa":"images/sets/md/jp/91.jpg","imageEn":"images/sets/md/en/91.jpg","enAvailable":true},{"id":"md-92","setIdJa":"md","nameJa":"メガルカリオex","nameEn":"Mega Lucario ex","supertype":"Pokémon","subtypes":["Stage 1","MEGA","ex"],"types":["Fighting"],"regulationMark":"I","imageJa":"images/sets/md/jp/92.jpg","imageEn":"images/sets/md/en/92.jpg","enAvailable":true},{"id":"md-93","setIdJa":"md","nameJa":"ヤンチャム","nameEn":"Pancham","supertype":"Pokémon","subtypes":["Basic"],"types":["Fighting"],"regulationMark":"I","imageJa":"images/sets/md/jp/93.jpg","imageEn":"images/sets/md/en/93.jpg","enAvailable":true},{"id":"md-94","setIdJa":"md","nameJa":"メガルチャブルex","nameEn":"Mega Hawlucha ex","supertype":"Pokémon","subtypes":["Basic","MEGA","ex"],"types":["Fighting"],"regulationMark":"I","imageJa":"images/sets/md/jp/94.jpg","imageEn":"images/sets/md/en/94.jpg","enAvailable":true},{"id":"md-95","setIdJa":"md","nameJa":"タンドン","nameEn":"Rolycoly","supertype":"Pokémon","subtypes":["Basic"],"types":["Fighting"],"regulationMark":"I","imageJa":"images/sets/md/jp/95.jpg","imageEn":"images/sets/md/en/95.jpg","enAvailable":true},{"id":"md-96","setIdJa":"md","nameJa":"トロッゴン","nameEn":"Carkol","supertype":"Pokémon","subtypes":["Stage 1"],"types":["Fighting"],"regulationMark":"I","imageJa":"images/sets/md/jp/96.jpg","imageEn":"images/sets/md/en/96.jpg","enAvailable":true},{"id":"md-97","setIdJa":"md","nameJa":"セキタンザン","nameEn":"Coalossal","supertype":"Pokémon","subtypes":["Stage 2"],"types":["Fighting"],"regulationMark":"I","imageJa":"images/sets/md/jp/97.jpg","imageEn":"images/sets/md/en/97.jpg","enAvailable":true},{"id":"md-98","setIdJa":"md","nameJa":"イイネイヌ","nameEn":"Okidogi","supertype":"Pokémon","subtypes":["Basic"],"types":["Fighting"],"regulationMark":"I","imageJa":"images/sets/md/jp/98.jpg","imageEn":"images/sets/md/en/98.jpg","enAvailable":true},{"id":"md-99","setIdJa":"md","nameJa":"ロケット団のズバット","nameEn":"Team Rocket's Zubat","supertype":"Pokémon","subtypes":["Basic"],"types":["Darkness"],"regulationMark":"I","imageJa":"images/sets/md/jp/99.jpg","imageEn":"images/sets/md/en/99.jpg","enAvailable":true},{"id":"md-100","setIdJa":"md","nameJa":"ロケット団のゴルバット","nameEn":"Team Rocket's Golbat","supertype":"Pokémon","subtypes":["Stage 1"],"types":["Darkness"],"regulationMark":"I","imageJa":"images/sets/md/jp/100.jpg","imageEn":"images/sets/md/en/100.jpg","enAvailable":true},{"id":"md-101","setIdJa":"md","nameJa":"ロケット団のクロバットex","nameEn":"Team Rocket's Crobat ex","supertype":"Pokémon","subtypes":["Stage 2","ex"],"types":["Darkness"],"regulationMark":"I","imageJa":"images/sets/md/jp/101.jpg","imageEn":"images/sets/md/en/101.jpg","enAvailable":true},{"id":"md-102","setIdJa":"md","nameJa":"ロケット団のヤミカラス","nameEn":"Team Rocket's Murkrow","supertype":"Pokémon","subtypes":["Basic"],"types":["Darkness"],"regulationMark":"I","imageJa":"images/sets/md/jp/102.jpg","imageEn":"images/sets/md/en/102.jpg","enAvailable":true},{"id":"md-103","setIdJa":"md","nameJa":"ロケット団のドンカラス","nameEn":"Team Rocket's Honchkrow","supertype":"Pokémon","subtypes":["Stage 1"],"types":["Darkness"],"regulationMark":"I","imageJa":"images/sets/md/jp/103.jpg","imageEn":"images/sets/md/en/103.jpg","enAvailable":true},{"id":"md-104","setIdJa":"md","nameJa":"ロケット団のニューラ","nameEn":"Team Rocket's Sneasel","supertype":"Pokémon","subtypes":["Basic"],"types":["Darkness"],"regulationMark":"I","imageJa":"images/sets/md/jp/104.jpg","imageEn":"images/sets/md/en/104.jpg","enAvailable":true},{"id":"md-105","setIdJa":"md","nameJa":"ガルジグザグマ","nameEn":"Galarian Zigzagoon","supertype":"Pokémon","subtypes":["Basic"],"types":["Darkness"],"regulationMark":"I","imageJa":"images/sets/md/jp/105.jpg","imageEn":"images/sets/md/en/105.jpg","enAvailable":true},{"id":"md-106","setIdJa":"md","nameJa":"ガルマッスグマ","nameEn":"Galarian Linoone","supertype":"Pokémon","subtypes":["Stage 1"],"types":["Darkness"],"regulationMark":"I","imageJa":"images/sets/md/jp/106.jpg","imageEn":"images/sets/md/en/106.jpg","enAvailable":true},{"id":"md-107","setIdJa":"md","nameJa":"ガルタチフサグマ","nameEn":"Galarian Obstagoon","supertype":"Pokémon","subtypes":["Stage 2"],"types":["Darkness"],"regulationMark":"I","imageJa":"images/sets/md/jp/107.jpg","imageEn":"images/sets/md/en/107.jpg","enAvailable":true},{"id":"md-108","setIdJa":"md","nameJa":"シロナのミカルゲ","nameEn":"Cynthia's Spiritomb","supertype":"Pokémon","subtypes":["Basic"],"types":["Darkness"],"regulationMark":"I","imageJa":"images/sets/md/jp/108.jpg","imageEn":"images/sets/md/en/108.jpg","enAvailable":true},{"id":"md-109","setIdJa":"md","nameJa":"ズルッグ","nameEn":"Scraggy","supertype":"Pokémon","subtypes":["Basic"],"types":["Darkness"],"regulationMark":"I","imageJa":"images/sets/md/jp/109.jpg","imageEn":"images/sets/md/en/109.jpg","enAvailable":true},{"id":"md-110","setIdJa":"md","nameJa":"メガズルズキンex","nameEn":"Mega Scrafty ex","supertype":"Pokémon","subtypes":["Stage 1","MEGA","ex"],"types":["Darkness"],"regulationMark":"I","imageJa":"images/sets/md/jp/110.jpg","imageEn":"images/sets/md/en/110.jpg","enAvailable":true},{"id":"md-111","setIdJa":"md","nameJa":"Nのゾロア","nameEn":"N's Zorua","supertype":"Pokémon","subtypes":["Basic"],"types":["Darkness"],"regulationMark":"I","imageJa":"images/sets/md/jp/111.jpg","imageEn":"images/sets/md/en/111.jpg","enAvailable":true},{"id":"md-112","setIdJa":"md","nameJa":"Nのゾロアークex","nameEn":"N's Zoroark ex","supertype":"Pokémon","subtypes":["Stage 1","ex"],"types":["Darkness"],"regulationMark":"I","imageJa":"images/sets/md/jp/112.jpg","imageEn":"images/sets/md/en/112.jpg","enAvailable":true},{"id":"md-113","setIdJa":"md","nameJa":"ゴロンダ","nameEn":"Pangoro","supertype":"Pokémon","subtypes":["Stage 1"],"types":["Darkness"],"regulationMark":"I","imageJa":"images/sets/md/jp/113.jpg","imageEn":"images/sets/md/en/113.jpg","enAvailable":true},{"id":"md-114","setIdJa":"md","nameJa":"キチキギスex","nameEn":"Fezandipiti ex","supertype":"Pokémon","subtypes":["Basic","ex"],"types":["Darkness"],"regulationMark":"H","imageJa":"images/sets/md/jp/114.jpg","imageEn":"images/sets/md/en/114.jpg","enAvailable":true},{"id":"md-115","setIdJa":"md","nameJa":"モモワロウ","nameEn":"Pecharunt","supertype":"Pokémon","subtypes":["Basic"],"types":["Darkness"],"regulationMark":"I","imageJa":"images/sets/md/jp/115.jpg","imageEn":"images/sets/md/en/115.jpg","enAvailable":true},{"id":"md-116","setIdJa":"md","nameJa":"コマタナ","nameEn":"Pawniard","supertype":"Pokémon","subtypes":["Basic"],"types":["Metal"],"regulationMark":"I","imageJa":"images/sets/md/jp/116.jpg","imageEn":"images/sets/md/en/116.jpg","enAvailable":true},{"id":"md-117","setIdJa":"md","nameJa":"キリキザン","nameEn":"Bisharp","supertype":"Pokémon","subtypes":["Stage 1"],"types":["Metal"],"regulationMark":"I","imageJa":"images/sets/md/jp/117.jpg","imageEn":"images/sets/md/en/117.jpg","enAvailable":true},{"id":"md-118","setIdJa":"md","nameJa":"ドドゲザン","nameEn":"Kingambit","supertype":"Pokémon","subtypes":["Stage 2"],"types":["Metal"],"regulationMark":"I","imageJa":"images/sets/md/jp/118.jpg","imageEn":"images/sets/md/en/118.jpg","enAvailable":true},{"id":"md-119","setIdJa":"md","nameJa":"ゲノセクトex","nameEn":"Genesect ex","supertype":"Pokémon","subtypes":["Basic","ex"],"types":["Metal"],"regulationMark":"I","imageJa":"images/sets/md/jp/119.jpg","imageEn":"images/sets/md/en/119.jpg","enAvailable":true},{"id":"md-120","setIdJa":"md","nameJa":"マギアナ","nameEn":"Magearna","supertype":"Pokémon","subtypes":["Basic"],"types":["Metal"],"regulationMark":"I","imageJa":"images/sets/md/jp/120.jpg","imageEn":"images/sets/md/en/120.jpg","enAvailable":true},{"id":"md-121","setIdJa":"md","nameJa":"ジュラルドン","nameEn":"Duraludon","supertype":"Pokémon","subtypes":["Basic"],"types":["Metal"],"regulationMark":"H","imageJa":"images/sets/md/jp/121.jpg","imageEn":"images/sets/md/en/121.jpg","enAvailable":true},{"id":"md-122","setIdJa":"md","nameJa":"ブリジュラスex","nameEn":"Archaludon ex","supertype":"Pokémon","subtypes":["Stage 1","ex"],"types":["Metal"],"regulationMark":"H","imageJa":"images/sets/md/jp/122.jpg","imageEn":"images/sets/md/en/122.jpg","enAvailable":true},{"id":"md-123","setIdJa":"md","nameJa":"ホップのザシアンex","nameEn":"Hop's Zacian ex","supertype":"Pokémon","subtypes":["Basic","ex"],"types":["Metal"],"regulationMark":"I","imageJa":"images/sets/md/jp/123.jpg","imageEn":"images/sets/md/en/123.jpg","enAvailable":true},{"id":"md-124","setIdJa":"md","nameJa":"ミニリュウ","nameEn":"Dratini","supertype":"Pokémon","subtypes":["Basic"],"types":["Dragon"],"regulationMark":"I","imageJa":"images/sets/md/jp/124.jpg","imageEn":"images/sets/md/en/124.jpg","enAvailable":true},{"id":"md-125","setIdJa":"md","nameJa":"ハクリュー","nameEn":"Dragonair","supertype":"Pokémon","subtypes":["Stage 1"],"types":["Dragon"],"regulationMark":"I","imageJa":"images/sets/md/jp/125.jpg","imageEn":"images/sets/md/en/125.jpg","enAvailable":true},{"id":"md-126","setIdJa":"md","nameJa":"メガカイリューex","nameEn":"Mega Dragonite ex","supertype":"Pokémon","subtypes":["Stage 2","MEGA","ex"],"types":["Dragon"],"regulationMark":"I","imageJa":"images/sets/md/jp/126.jpg","imageEn":"images/sets/md/en/126.jpg","enAvailable":true},{"id":"md-127","setIdJa":"md","nameJa":"レックウザ","nameEn":"Rayquaza","supertype":"Pokémon","subtypes":["Basic"],"types":["Dragon"],"regulationMark":"I","imageJa":"images/sets/md/jp/127.jpg","imageEn":"images/sets/md/en/127.jpg","enAvailable":true},{"id":"md-128","setIdJa":"md","nameJa":"Nのレシラム","nameEn":"N's Reshiram","supertype":"Pokémon","subtypes":["Basic"],"types":["Dragon"],"regulationMark":"I","imageJa":"images/sets/md/jp/128.jpg","imageEn":"images/sets/md/en/128.jpg","enAvailable":true},{"id":"md-129","setIdJa":"md","nameJa":"Nのゼクロム","nameEn":"N's Zekrom","supertype":"Pokémon","subtypes":["Basic"],"types":["Dragon"],"regulationMark":"I","imageJa":"images/sets/md/jp/129.jpg","imageEn":"images/sets/md/en/129.jpg","enAvailable":true},{"id":"md-130","setIdJa":"md","nameJa":"オンバット","nameEn":"Noibat","supertype":"Pokémon","subtypes":["Basic"],"types":["Dragon"],"regulationMark":"I","imageJa":"images/sets/md/jp/130.jpg","imageEn":"images/sets/md/en/130.jpg","enAvailable":true},{"id":"md-131","setIdJa":"md","nameJa":"オンバーン","nameEn":"Noivern","supertype":"Pokémon","subtypes":["Stage 1"],"types":["Dragon"],"regulationMark":"I","imageJa":"images/sets/md/jp/131.jpg","imageEn":"images/sets/md/en/131.jpg","enAvailable":true},{"id":"md-132","setIdJa":"md","nameJa":"ドラメシャ","nameEn":"Dreepy","supertype":"Pokémon","subtypes":["Basic"],"types":["Dragon"],"regulationMark":"H","imageJa":"images/sets/md/jp/132.jpg","imageEn":"images/sets/md/en/132.jpg","enAvailable":true},{"id":"md-133","setIdJa":"md","nameJa":"ドロンチ","nameEn":"Drakloak","supertype":"Pokémon","subtypes":["Stage 1"],"types":["Dragon"],"regulationMark":"H","imageJa":"images/sets/md/jp/133.jpg","imageEn":"images/sets/md/en/133.jpg","enAvailable":true},{"id":"md-134","setIdJa":"md","nameJa":"ドラパルトex","nameEn":"Dragapult ex","supertype":"Pokémon","subtypes":["Stage 2","Tera","ex"],"types":["Dragon"],"regulationMark":"H","imageJa":"images/sets/md/jp/134.jpg","imageEn":"images/sets/md/en/134.jpg","enAvailable":true},{"id":"md-135","setIdJa":"md","nameJa":"シャリタツ","nameEn":"Tatsugiri","supertype":"Pokémon","subtypes":["Basic"],"types":["Dragon"],"regulationMark":"H","imageJa":"images/sets/md/jp/135.jpg","imageEn":"images/sets/md/en/135.jpg","enAvailable":true},{"id":"md-136","setIdJa":"md","nameJa":"ホップのカビゴン","nameEn":"Hop's Snorlax","supertype":"Pokémon","subtypes":["Basic"],"types":["Colorless"],"regulationMark":"I","imageJa":"images/sets/md/jp/136.jpg","imageEn":"images/sets/md/en/136.jpg","enAvailable":true},{"id":"md-137","setIdJa":"md","nameJa":"ホーホー","nameEn":"Hoothoot","supertype":"Pokémon","subtypes":["Basic"],"types":["Colorless"],"regulationMark":"H","imageJa":"images/sets/md/jp/137.jpg","imageEn":"images/sets/md/en/137.jpg","enAvailable":true},{"id":"md-138","setIdJa":"md","nameJa":"ヨルノズク","nameEn":"Noctowl","supertype":"Pokémon","subtypes":["Stage 1"],"types":["Colorless"],"regulationMark":"H","imageJa":"images/sets/md/jp/138.jpg","imageEn":"images/sets/md/en/138.jpg","enAvailable":true},{"id":"md-139","setIdJa":"md","nameJa":"スピンロトム","nameEn":"Fan Rotom","supertype":"Pokémon","subtypes":["Basic"],"types":["Colorless"],"regulationMark":"H","imageJa":"images/sets/md/jp/139.jpg","imageEn":"images/sets/md/en/139.jpg","enAvailable":true},{"id":"md-140","setIdJa":"md","nameJa":"バッフロン","nameEn":"Bouffalant","supertype":"Pokémon","subtypes":["Basic"],"types":["Colorless"],"regulationMark":"H","imageJa":"images/sets/md/jp/140.jpg","imageEn":"images/sets/md/en/140.jpg","enAvailable":true},{"id":"md-141","setIdJa":"md","nameJa":"ホップのウールー","nameEn":"Hop's Wooloo","supertype":"Pokémon","subtypes":["Basic"],"types":["Colorless"],"regulationMark":"I","imageJa":"images/sets/md/jp/141.jpg","imageEn":"images/sets/md/en/141.jpg","enAvailable":true},{"id":"md-142","setIdJa":"md","nameJa":"ホップのバイウールー","nameEn":"Hop's Dubwool","supertype":"Pokémon","subtypes":["Stage 1"],"types":["Colorless"],"regulationMark":"I","imageJa":"images/sets/md/jp/142.jpg","imageEn":"images/sets/md/en/142.jpg","enAvailable":true},{"id":"md-143","setIdJa":"md","nameJa":"ホップのウッウ","nameEn":"Hop's Cramorant","supertype":"Pokémon","subtypes":["Basic"],"types":["Colorless"],"regulationMark":"I","imageJa":"images/sets/md/jp/143.jpg","imageEn":"images/sets/md/en/143.jpg","enAvailable":true},{"id":"md-144","setIdJa":"md","nameJa":"テラパゴス","nameEn":"Terapagos","supertype":"Pokémon","subtypes":["Basic"],"types":["Colorless"],"regulationMark":"H","imageJa":"images/sets/md/jp/144.jpg","imageEn":"images/sets/md/en/144.jpg","enAvailable":true},{"id":"md-145","setIdJa":"md","nameJa":"テラパゴスex","nameEn":"Terapagos ex","supertype":"Pokémon","subtypes":["Basic","Tera","ex"],"types":["Colorless"],"regulationMark":"H","imageJa":"images/sets/md/jp/145.jpg","imageEn":"images/sets/md/en/145.jpg","enAvailable":true},{"id":"md-146","setIdJa":"md","nameJa":"Nのポイントアップ","nameEn":"N's PP Up","supertype":"Trainer","subtypes":["Item"],"types":[],"regulationMark":"I","imageJa":"images/sets/md/jp/146.jpg","imageEn":"images/sets/md/en/146.jpg","enAvailable":true},{"id":"md-147","setIdJa":"md","nameJa":"エネルギーリサイクル","nameEn":"Energy Recycler","supertype":"Trainer","subtypes":["Item"],"types":[],"regulationMark":"I","imageJa":"images/sets/md/jp/147.jpg","imageEn":"images/sets/md/en/147.jpg","enAvailable":true},{"id":"md-148","setIdJa":"md","nameJa":"改造ハンマー","nameEn":"Enhanced Hammer","supertype":"Trainer","subtypes":["Item"],"types":[],"regulationMark":"H","imageJa":"images/sets/md/jp/148.jpg","imageEn":"images/sets/md/en/148.jpg","enAvailable":true},{"id":"md-149","setIdJa":"md","nameJa":"ガラスのラッパ","nameEn":"Glass Trumpet","supertype":"Trainer","subtypes":["Item"],"types":[],"regulationMark":"H","imageJa":"images/sets/md/jp/149.jpg","imageEn":"images/sets/md/en/149.jpg","enAvailable":true},{"id":"md-150","setIdJa":"md","nameJa":"せいなるはい","nameEn":"Sacred Ash","supertype":"Trainer","subtypes":["Item"],"types":[],"regulationMark":"I","imageJa":"images/sets/md/jp/150.jpg","imageEn":"images/sets/md/en/150.jpg","enAvailable":true},{"id":"md-151","setIdJa":"md","nameJa":"ツールスクラッパー","nameEn":"Tool Scrapper","supertype":"Trainer","subtypes":["Item"],"types":[],"regulationMark":"I","imageJa":"images/sets/md/jp/151.jpg","imageEn":"images/sets/md/en/151.jpg","enAvailable":true},{"id":"md-152","setIdJa":"md","nameJa":"テラスタルオーブ","nameEn":"Tera Orb","supertype":"Trainer","subtypes":["Item"],"types":[],"regulationMark":"H","imageJa":"images/sets/md/jp/152.jpg","imageEn":"images/sets/md/en/152.jpg","enAvailable":true},{"id":"md-153","setIdJa":"md","nameJa":"なかよしポフィン","nameEn":"Buddy-Buddy Poffin","supertype":"Trainer","subtypes":["Item"],"types":[],"regulationMark":"H","imageJa":"images/sets/md/jp/153.jpg","imageEn":"images/sets/md/en/153.jpg","enAvailable":true},{"id":"md-154","setIdJa":"md","nameJa":"パワープロテイン","nameEn":"Premium Power Pro","supertype":"Trainer","subtypes":["Item"],"types":[],"regulationMark":"I","imageJa":"images/sets/md/jp/154.jpg","imageEn":"images/sets/md/en/154.jpg","enAvailable":true},{"id":"md-155","setIdJa":"md","nameJa":"ファイトゴング","nameEn":"Fighting Gong","supertype":"Trainer","subtypes":["Item"],"types":[],"regulationMark":"I","imageJa":"images/sets/md/jp/155.jpg","imageEn":"images/sets/md/en/155.jpg","enAvailable":true},{"id":"md-156","setIdJa":"md","nameJa":"ホップのバッグ","nameEn":"Hop's Bag","supertype":"Trainer","subtypes":["Item"],"types":[],"regulationMark":"I","imageJa":"images/sets/md/jp/156.jpg","imageEn":"images/sets/md/en/156.jpg","enAvailable":true},{"id":"md-157","setIdJa":"md","nameJa":"むしとりセット","nameEn":"Bug Catching Set","supertype":"Trainer","subtypes":["Item"],"types":[],"regulationMark":"H","imageJa":"images/sets/md/jp/157.jpg","imageEn":"images/sets/md/en/157.jpg","enAvailable":true},{"id":"md-158","setIdJa":"md","nameJa":"メガシグナル","nameEn":"Mega Signal","supertype":"Trainer","subtypes":["Item"],"types":[],"regulationMark":"I","imageJa":"images/sets/md/jp/158.jpg","imageEn":"images/sets/md/en/158.jpg","enAvailable":true},{"id":"md-159","setIdJa":"md","nameJa":"夜のタンカ","nameEn":"Night Stretcher","supertype":"Trainer","subtypes":["Item"],"types":[],"regulationMark":"H","imageJa":"images/sets/md/jp/159.jpg","imageEn":"images/sets/md/en/159.jpg","enAvailable":true},{"id":"md-160","setIdJa":"md","nameJa":"ロケット団のレシーバー","nameEn":"Team Rocket's Transceiver","supertype":"Trainer","subtypes":["Item"],"types":[],"regulationMark":"I","imageJa":"images/sets/md/jp/160.jpg","imageEn":"images/sets/md/en/160.jpg","enAvailable":true},{"id":"md-161","setIdJa":"md","nameJa":"カウンターゲイン","nameEn":"Counter Gain","supertype":"Trainer","subtypes":["Tool"],"types":[],"regulationMark":"H","imageJa":"images/sets/md/jp/161.jpg","imageEn":"images/sets/md/en/161.jpg","enAvailable":true},{"id":"md-162","setIdJa":"md","nameJa":"シロナのパワーウエイト","nameEn":"Cynthia's Power Weight","supertype":"Trainer","subtypes":["Tool"],"types":[],"regulationMark":"I","imageJa":"images/sets/md/jp/162.jpg","imageEn":"images/sets/md/en/162.jpg","enAvailable":true},{"id":"md-163","setIdJa":"md","nameJa":"でんきだま","nameEn":"Light Ball","supertype":"Trainer","subtypes":["Tool"],"types":[],"regulationMark":"I","imageJa":"images/sets/md/jp/163.jpg","imageEn":"images/sets/md/en/163.jpg","enAvailable":true},{"id":"md-164","setIdJa":"md","nameJa":"ぶあついうろこ","nameEn":"Thick Scale","supertype":"Trainer","subtypes":["Tool"],"types":[],"regulationMark":"I","imageJa":"images/sets/md/jp/164.jpg","imageEn":"images/sets/md/en/164.jpg","enAvailable":true},{"id":"md-165","setIdJa":"md","nameJa":"ふうせん","nameEn":"Air Balloon","supertype":"Trainer","subtypes":["Tool"],"types":[],"regulationMark":"I","imageJa":"images/sets/md/jp/165.jpg","imageEn":"images/sets/md/en/165.jpg","enAvailable":true},{"id":"md-166","setIdJa":"md","nameJa":"ブレイブバングル","nameEn":"Brave Bangle","supertype":"Trainer","subtypes":["Tool"],"types":[],"regulationMark":"I","imageJa":"images/sets/md/jp/166.jpg","imageEn":"images/sets/md/en/166.jpg","enAvailable":true},{"id":"md-167","setIdJa":"md","nameJa":"ホップのこだわりハチマキ","nameEn":"Hop's Choice Band","supertype":"Trainer","subtypes":["Tool"],"types":[],"regulationMark":"I","imageJa":"images/sets/md/jp/167.jpg","imageEn":"images/sets/md/en/167.jpg","enAvailable":true},{"id":"md-168","setIdJa":"md","nameJa":"アイリスの闘志","nameEn":"Iris's Fighting Spirit","supertype":"Trainer","subtypes":["Supporter"],"types":[],"regulationMark":"I","imageJa":"images/sets/md/jp/168.jpg","imageEn":"images/sets/md/en/168.jpg","enAvailable":true},{"id":"md-169","setIdJa":"md","nameJa":"アセロラのいたずら","nameEn":"Acerola's Mischief","supertype":"Trainer","subtypes":["Supporter"],"types":[],"regulationMark":"I","imageJa":"images/sets/md/jp/169.jpg","imageEn":"images/sets/md/en/169.jpg","enAvailable":true},{"id":"md-170","setIdJa":"md","nameJa":"カナリィ","nameEn":"Canari","supertype":"Trainer","subtypes":["Supporter"],"types":[],"regulationMark":"I","imageJa":"images/sets/md/jp/170.jpg","imageEn":"images/sets/md/en/170.jpg","enAvailable":true},{"id":"md-171","setIdJa":"md","nameJa":"サーファー","nameEn":"Surfer","supertype":"Trainer","subtypes":["Supporter"],"types":[],"regulationMark":"H","imageJa":"images/sets/md/jp/171.jpg","imageEn":"images/sets/md/en/171.jpg","enAvailable":true},{"id":"md-172","setIdJa":"md","nameJa":"トウコ","nameEn":"Hilda","supertype":"Trainer","subtypes":["Supporter"],"types":[],"regulationMark":"I","imageJa":"images/sets/md/jp/172.jpg","imageEn":"images/sets/md/en/172.jpg","enAvailable":true},{"id":"md-173","setIdJa":"md","nameJa":"バーベナとヘレナ","nameEn":"Anthea & Concordia","supertype":"Trainer","subtypes":["Supporter"],"types":[],"regulationMark":"I","imageJa":"images/sets/md/jp/173.jpg","imageEn":"images/sets/md/en/173.jpg","enAvailable":true},{"id":"md-174","setIdJa":"md","nameJa":"ヒビキの冒険","nameEn":"Ethan's Adventure","supertype":"Trainer","subtypes":["Supporter"],"types":[],"regulationMark":"I","imageJa":"images/sets/md/jp/174.jpg","imageEn":"images/sets/md/en/174.jpg","enAvailable":true},{"id":"md-175","setIdJa":"md","nameJa":"リーリエの決心","nameEn":"Lillie's Determination","supertype":"Trainer","subtypes":["Supporter"],"types":[],"regulationMark":"I","imageJa":"images/sets/md/jp/175.jpg","imageEn":"images/sets/md/en/175.jpg","enAvailable":true},{"id":"md-176","setIdJa":"md","nameJa":"ロケット団のアテナ","nameEn":"Team Rocket's Ariana","supertype":"Trainer","subtypes":["Supporter"],"types":[],"regulationMark":"I","imageJa":"images/sets/md/jp/176.jpg","imageEn":"images/sets/md/en/176.jpg","enAvailable":true},{"id":"md-177","setIdJa":"md","nameJa":"ロケット団のアポロ","nameEn":"Team Rocket's Archer","supertype":"Trainer","subtypes":["Supporter"],"types":[],"regulationMark":"I","imageJa":"images/sets/md/jp/177.jpg","imageEn":"images/sets/md/en/177.jpg","enAvailable":true},{"id":"md-178","setIdJa":"md","nameJa":"ロケット団のサカキ","nameEn":"Team Rocket's Giovanni","supertype":"Trainer","subtypes":["Supporter"],"types":[],"regulationMark":"I","imageJa":"images/sets/md/jp/178.jpg","imageEn":"images/sets/md/en/178.jpg","enAvailable":true},{"id":"md-179","setIdJa":"md","nameJa":"ロケット団のラムダ","nameEn":"Team Rocket's Petrel","supertype":"Trainer","subtypes":["Supporter"],"types":[],"regulationMark":"I","imageJa":"images/sets/md/jp/179.jpg","imageEn":"images/sets/md/en/179.jpg","enAvailable":true},{"id":"md-180","setIdJa":"md","nameJa":"ロケット団のランス","nameEn":"Team Rocket's Proton","supertype":"Trainer","subtypes":["Supporter"],"types":[],"regulationMark":"I","imageJa":"images/sets/md/jp/180.jpg","imageEn":"images/sets/md/en/180.jpg","enAvailable":true},{"id":"md-181","setIdJa":"md","nameJa":"Nの城","nameEn":"N's Castle","supertype":"Trainer","subtypes":["Stadium"],"types":[],"regulationMark":"I","imageJa":"images/sets/md/jp/181.jpg","imageEn":"images/sets/md/en/181.jpg","enAvailable":true},{"id":"md-182","setIdJa":"md","nameJa":"活力の森","nameEn":"Forest of Vitality","supertype":"Trainer","subtypes":["Stadium"],"types":[],"regulationMark":"I","imageJa":"images/sets/md/jp/182.jpg","imageEn":"images/sets/md/en/182.jpg","enAvailable":true},{"id":"md-183","setIdJa":"md","nameJa":"グラビティーマウンテン","nameEn":"Gravity Mountain","supertype":"Trainer","subtypes":["Stadium"],"types":[],"regulationMark":"H","imageJa":"images/sets/md/jp/183.jpg","imageEn":"images/sets/md/en/183.jpg","enAvailable":true},{"id":"md-184","setIdJa":"md","nameJa":"ゼロの大空洞","nameEn":"Area Zero Underdepths","supertype":"Trainer","subtypes":["Stadium"],"types":[],"regulationMark":"H","imageJa":"images/sets/md/jp/184.jpg","imageEn":"images/sets/md/en/184.jpg","enAvailable":true},{"id":"md-185","setIdJa":"md","nameJa":"ハッコウシティ","nameEn":"Levincia","supertype":"Trainer","subtypes":["Stadium"],"types":[],"regulationMark":"I","imageJa":"images/sets/md/jp/185.jpg","imageEn":"images/sets/md/en/185.jpg","enAvailable":true},{"id":"md-186","setIdJa":"md","nameJa":"ハロンタウン","nameEn":"Postwick","supertype":"Trainer","subtypes":["Stadium"],"types":[],"regulationMark":"I","imageJa":"images/sets/md/jp/186.jpg","imageEn":"images/sets/md/en/186.jpg","enAvailable":true},{"id":"md-187","setIdJa":"md","nameJa":"ミステリーガーデン","nameEn":"Mystery Garden","supertype":"Trainer","subtypes":["Stadium"],"types":[],"regulationMark":"I","imageJa":"images/sets/md/jp/187.jpg","imageEn":"images/sets/md/en/187.jpg","enAvailable":true},{"id":"md-188","setIdJa":"md","nameJa":"夜の鉱山","nameEn":"Nighttime Mine","supertype":"Trainer","subtypes":["Stadium"],"types":[],"regulationMark":"I","imageJa":"images/sets/md/jp/188.jpg","imageEn":"images/sets/md/en/188.jpg","enAvailable":true},{"id":"md-189","setIdJa":"md","nameJa":"ロケット団の監視塔","nameEn":"Team Rocket's Watchtower","supertype":"Trainer","subtypes":["Stadium"],"types":[],"regulationMark":"I","imageJa":"images/sets/md/jp/189.jpg","imageEn":"images/sets/md/en/189.jpg","enAvailable":true},{"id":"md-190","setIdJa":"md","nameJa":"ロケット団のファクトリー","nameEn":"Team Rocket's Factory","supertype":"Trainer","subtypes":["Stadium"],"types":[],"regulationMark":"I","imageJa":"images/sets/md/jp/190.jpg","imageEn":"images/sets/md/en/190.jpg","enAvailable":true},{"id":"md-191","setIdJa":"md","nameJa":"イグニッションエネルギー","nameEn":"Ignition Energy","supertype":"Energy","subtypes":["Special"],"types":[],"regulationMark":"I","imageJa":"images/sets/md/jp/191.jpg","imageEn":"images/sets/md/en/191.jpg","enAvailable":true},{"id":"md-192","setIdJa":"md","nameJa":"プリズムエネルギー","nameEn":"Prism Energy","supertype":"Energy","subtypes":["Special"],"types":[],"regulationMark":"I","imageJa":"images/sets/md/jp/192.jpg","imageEn":"images/sets/md/en/192.jpg","enAvailable":true},{"id":"md-193","setIdJa":"md","nameJa":"ロケット団エネルギー","nameEn":"Team Rocket's Energy","supertype":"Energy","subtypes":["Special"],"types":[],"regulationMark":"I","imageJa":"images/sets/md/jp/193.jpg","imageEn":"images/sets/md/en/193.jpg","enAvailable":true}]